Workbook

Sheet Cover
B2: ESWE Versorgungs AG – Financial Model 2021–2025
B4: HGB-Einzelabschluss · Geschäftsjahre 2021 bis 2025
B5: Alle Beträge in EUR Mio., sofern nicht anders vermerkt
B7: Inhalt | C7: Inhalt / Beschreibung
B8: Overview FS | C8: Verdichtete Ertrags-, Finanz- und Vermögenslage sowie Kennzahlen 2021–2025
B9: ESWE Bilanz | C9: Bilanz zum 31. Dezember, Gliederung gem. § 266 HGB
B10: ESWE GuV | C10: Gewinn- und Verlustrechnung, Gesamtkostenverfahren gem. § 275 Abs. 2 HGB
B11: ESWE Cashflow | C11: Kapitalflussrechnung nach DRS 21 (veröffentlichte Kurzfassung)
B12: ESWE KPIs | C12: Key Financials – Marge, EBITDA, Net Debt, Eigenkapitalquote, Capex
B13: ESWE Capex Revenue | C13: Investitionen und Umsatzerlöse nach Unternehmensbereichen, Absatzmengen
B14: Quellen & Hinweise | C14: Quellenverzeichnis, Farbkonvention, Abweichungen und Umgliederungen
B16: Farbkonvention
B17: Blau | C17: Eingabewert direkt aus dem Jahresabschluss bzw. Geschäftsbericht
B18: Schwarz | C18: Formel innerhalb des Blattes
B19: Grün | C19: Verweis auf ein anderes Blatt dieser Mappe
B20: Grau kursiv | C20: Position im betreffenden Jahr nicht separat ausgewiesen (n.a.)
B22: Sämtliche Zwischen- und Endsummen sind als Formeln hinterlegt und nirgends hartcodiert. Die Mappe folgt in Aufbau, Schrift, Farbgebung und Zahlenformaten dem Financial Model der evm AG / enm (evm_enm_financial_model_2020_2024_v5).

Sheet Output>>

Sheet Overview FS
B2: ESWE Versorgungs AG – Financial Overview 2021–2025
B3: EUR Mio. / % / x | C3: 2021 | D3: 2022 | E3: 2023 | F3: 2024 | G3: 2025
B4: Umsatzerlöse | C4: ='ESWE KPIs'!C5 | D4: ='ESWE KPIs'!D5 | E4: ='ESWE KPIs'!E5 | F4: ='ESWE KPIs'!F5 | G4: ='ESWE KPIs'!G5
B5: Gesamtleistung | C5: ='ESWE KPIs'!C6 | D5: ='ESWE KPIs'!D6 | E5: ='ESWE KPIs'!E6 | F5: ='ESWE KPIs'!F6 | G5: ='ESWE KPIs'!G6
B6: Rohertrag | C6: ='ESWE KPIs'!C7 | D6: ='ESWE KPIs'!D7 | E6: ='ESWE KPIs'!E7 | F6: ='ESWE KPIs'!F7 | G6: ='ESWE KPIs'!G7
B7: Rohertragsmarge | C7: ='ESWE KPIs'!C8 | D7: ='ESWE KPIs'!D8 | E7: ='ESWE KPIs'!E8 | F7: ='ESWE KPIs'!F8 | G7: ='ESWE KPIs'!G8
B8: EBITDA | C8: ='ESWE KPIs'!C10 | D8: ='ESWE KPIs'!D10 | E8: ='ESWE KPIs'!E10 | F8: ='ESWE KPIs'!F10 | G8: ='ESWE KPIs'!G10
B9: Betriebliches Ergebnis | C9: ='ESWE KPIs'!C11 | D9: ='ESWE KPIs'!D11 | E9: ='ESWE KPIs'!E11 | F9: ='ESWE KPIs'!F11 | G9: ='ESWE KPIs'!G11
B10: Beteiligungsergebnis | C10: ='ESWE KPIs'!C12 | D10: ='ESWE KPIs'!D12 | E10: ='ESWE KPIs'!E12 | F10: ='ESWE KPIs'!F12 | G10: ='ESWE KPIs'!G12
B11: Ergebnis vor Steuern | C11: ='ESWE KPIs'!C14 | D11: ='ESWE KPIs'!D14 | E11: ='ESWE KPIs'!E14 | F11: ='ESWE KPIs'!F14 | G11: ='ESWE KPIs'!G14
B12: Jahresüberschuss | C12: ='ESWE KPIs'!C15 | D12: ='ESWE KPIs'!D15 | E12: ='ESWE KPIs'!E15 | F12: ='ESWE KPIs'!F15 | G12: ='ESWE KPIs'!G15
B14: Cashflow | C14: 2021 | D14: 2022 | E14: 2023 | F14: 2024 | G14: 2025
B15: Operating Cash Flow | C15: ='ESWE KPIs'!C17 | D15: ='ESWE KPIs'!D17 | E15: ='ESWE KPIs'!E17 | F15: ='ESWE KPIs'!F17 | G15: ='ESWE KPIs'!G17
B16: Investing Cash Flow | C16: ='ESWE KPIs'!C18 | D16: ='ESWE KPIs'!D18 | E16: ='ESWE KPIs'!E18 | F16: ='ESWE KPIs'!F18 | G16: ='ESWE KPIs'!G18
B17: Financing Cash Flow | C17: ='ESWE KPIs'!C19 | D17: ='ESWE KPIs'!D19 | E17: ='ESWE KPIs'!E19 | F17: ='ESWE KPIs'!F19 | G17: ='ESWE KPIs'!G19
B18: Cashflow gesamt | C18: =SUM(C15:C17) | D18: =SUM(D15:D17) | E18: =SUM(E15:E17) | F18: =SUM(F15:F17) | G18: =SUM(G15:G17)
B20: Vermögens- und Finanzlage | C20: 2021 | D20: 2022 | E20: 2023 | F20: 2024 | G20: 2025
B21: Bilanzsumme | C21: ='ESWE KPIs'!C22 | D21: ='ESWE KPIs'!D22 | E21: ='ESWE KPIs'!E22 | F21: ='ESWE KPIs'!F22 | G21: ='ESWE KPIs'!G22
B22: Eigenkapital | C22: ='ESWE KPIs'!C23 | D22: ='ESWE KPIs'!D23 | E22: ='ESWE KPIs'!E23 | F22: ='ESWE KPIs'!F23 | G22: ='ESWE KPIs'!G23
B23: Eigenkapitalquote | C23: ='ESWE KPIs'!C24 | D23: ='ESWE KPIs'!D24 | E23: ='ESWE KPIs'!E24 | F23: ='ESWE KPIs'!F24 | G23: ='ESWE KPIs'!G24
B24: Kassenbestand | C24: ='ESWE KPIs'!C27 | D24: ='ESWE KPIs'!D27 | E24: ='ESWE KPIs'!E27 | F24: ='ESWE KPIs'!F27 | G24: ='ESWE KPIs'!G27
B25: Finanzverbindlichkeiten | C25: ='ESWE KPIs'!C28 | D25: ='ESWE KPIs'!D28 | E25: ='ESWE KPIs'!E28 | F25: ='ESWE KPIs'!F28 | G25: ='ESWE KPIs'!G28
B26: Net Debt | C26: ='ESWE KPIs'!C29 | D26: ='ESWE KPIs'!D29 | E26: ='ESWE KPIs'!E29 | F26: ='ESWE KPIs'!F29 | G26: ='ESWE KPIs'!G29
B27: Net Debt / EBITDA | C27: ='ESWE KPIs'!C30 | D27: ='ESWE KPIs'!D30 | E27: ='ESWE KPIs'!E30 | F27: ='ESWE KPIs'!F30 | G27: ='ESWE KPIs'!G30
B28: Capex (Gesamtinvestitionen) | C28: ='ESWE KPIs'!C32 | D28: ='ESWE KPIs'!D32 | E28: ='ESWE KPIs'!E32 | F28: ='ESWE KPIs'!F32 | G28: ='ESWE KPIs'!G32
B30: Umsatzaufteilung | C30: 2021 | D30: 2022 | E30: 2023 | F30: 2024 | G30: 2025
B31: Stromversorgung (inkl. Handelsgeschäfte) | C31: ='ESWE Capex Revenue'!C7 | D31: ='ESWE Capex Revenue'!D7 | E31: ='ESWE Capex Revenue'!E7 | F31: ='ESWE Capex Revenue'!F7 | G31: ='ESWE Capex Revenue'!G7
B32: Gasversorgung (inkl. Handelsgeschäfte) | C32: ='ESWE Capex Revenue'!C8 | D32: ='ESWE Capex Revenue'!D8 | E32: ='ESWE Capex Revenue'!E8 | F32: ='ESWE Capex Revenue'!F8 | G32: ='ESWE Capex Revenue'!G8
B33: Wärmeversorgung | C33: ='ESWE Capex Revenue'!C9 | D33: ='ESWE Capex Revenue'!D9 | E33: ='ESWE Capex Revenue'!E9 | F33: ='ESWE Capex Revenue'!F9 | G33: ='ESWE Capex Revenue'!G9
B34: Betriebsführung Wasserversorgung | C34: ='ESWE Capex Revenue'!C10 | D34: ='ESWE Capex Revenue'!D10 | E34: ='ESWE Capex Revenue'!E10 | F34: ='ESWE Capex Revenue'!F10 | G34: ='ESWE Capex Revenue'!G10
B35: Wasserverkauf an WLW | C35: ='ESWE Capex Revenue'!C11 | D35: ='ESWE Capex Revenue'!D11 | E35: ='ESWE Capex Revenue'!E11 | F35: ='ESWE Capex Revenue'!F11 | G35: ='ESWE Capex Revenue'!G11
B36: Konzerninterne Dienstleistungen | C36: ='ESWE Capex Revenue'!C12 | D36: ='ESWE Capex Revenue'!D12 | E36: ='ESWE Capex Revenue'!E12 | F36: ='ESWE Capex Revenue'!F12 | G36: ='ESWE Capex Revenue'!G12
B37: Übrige Umsatzerlöse | C37: ='ESWE Capex Revenue'!C13 | D37: ='ESWE Capex Revenue'!D13 | E37: ='ESWE Capex Revenue'!E13 | F37: ='ESWE Capex Revenue'!F13 | G37: ='ESWE Capex Revenue'!G13
B38: Umsätze lt. GuV | C38: =SUM(C31:C37) | D38: =SUM(D31:D37) | E38: =SUM(E31:E37) | F38: =SUM(F31:F37) | G38: =SUM(G31:G37)
B40: Anteil Strom / Gas am Umsatz | C40: =IFERROR((C31+C32)/C38,0) | D40: =IFERROR((D31+D32)/D38,0) | E40: =IFERROR((E31+E32)/E38,0) | F40: =IFERROR((F31+F32)/F38,0) | G40: =IFERROR((G31+G32)/G38,0)
B42: Methodik: Net Debt = Verbindlichkeiten gegenüber Kreditinstituten abzüglich Kassenbestand und Guthaben bei Kreditinstituten. Intercompany-Finanzierungen, empfangene Ertragszuschüsse und Rückstellungen sind nicht einbezogen, da eine belastbare Trennung von operativen und finanzierungsbezogenen Positionen aus dem veröffentlichten Einzelabschluss nicht durchgängig möglich ist. Gesamtleistung = Umsatzerlöse zzgl. Bestandsveränderung und anderer aktivierter Eigenleistungen. Rohertrag = Gesamtleistung abzüglich Materialaufwand. EBITDA = Betriebliches Ergebnis zzgl. Abschreibungen auf immaterielle Vermögensgegenstände und Sachanlagen. Sämtliche Werte dieses Blattes sind Verweise (grün) auf die Detailblätter.
B45: Die Umsatzaufteilung folgt der im Geschäftsbericht 2025 verwendeten siebenzeiligen Gliederung. Für 2021 bis 2024 wurden die in den Jahresabschlüssen separat ausgewiesenen Positionen entsprechend zusammengefasst (Strom- und Gashandel in die jeweilige Sparte, Tankstelle und Auflösung empfangener Ertragszuschüsse in die übrigen Umsatzerlöse). Siehe Blatt „Quellen & Hinweise“.

Sheet Input>>

Sheet ESWE Bilanz
B2: ESWE Versorgungs AG – Bilanz zum 31. Dezember 2021–2025
B3: EUR Mio. | C3: 2021 | D3: =C3+1 | E3: =D3+1 | F3: =E3+1 | G3: =F3+1
B5: AKTIVA
B6: A. Anlagevermögen (1) | C6: =SUM(C7:C9) | D6: =SUM(D7:D9) | E6: =SUM(E7:E9) | F6: =SUM(F7:F9) | G6: =SUM(G7:G9)
B7: I. Immaterielle Vermögensgegenstände | C7: 1.044 | D7: 0.811 | E7: 0.658 | F7: 0.877 | G7: 0.764
B8: II. Sachanlagen | C8: 174.058 | D8: 189.12 | E8: 197.803 | F8: 209.24 | G8: 223.938
B9: III. Finanzanlagen | C9: 148.234 | D9: 170.186 | E9: 171.96 | F9: 165.19 | G9: 170.025
B11: B. Umlaufvermögen | C11: =SUM(C12:C14) | D11: =SUM(D12:D14) | E11: =SUM(E12:E14) | F11: =SUM(F12:F14) | G11: =SUM(G12:G14)
B12: I. Vorräte (2) | C12: 7.162 | D12: 8.158 | E12: 15.439 | F12: 18.356 | G12: 17.857
B13: II. Forderungen und sonstige Vermögensgegenstände (3) | C13: 48.391 | D13: 17.853 | E13: 46.747 | F13: 43.316 | G13: 63.663
B14: III. Kassenbestand und Guthaben bei Kreditinstituten | C14: 3.616 | D14: 30.611 | E14: 44.992 | F14: 21.543 | G14: 2.517
B16: C. Rechnungsabgrenzungsposten | C16: 2.468 | D16: 3.089 | E16: 3.588 | F16: 0.581 | G16: 0.819
B17: Bilanzsumme Aktiva | C17: =C6+C11+C16 | D17: =D6+D11+D16 | E17: =E6+E11+E16 | F17: =F6+F11+F16 | G17: =G6+G11+G16
B19: PASSIVA
B20: A. Eigenkapital (4) | C20: =SUM(C21:C24) | D20: =SUM(D21:D24) | E20: =SUM(E21:E24) | F20: =SUM(F21:F24) | G20: =SUM(G21:G24)
B21: I. Gezeichnetes Kapital | C21: 66.013 | D21: 66.013 | E21: 66.013 | F21: 66.013 | G21: 66.013
B22: II. Kapitalrücklage | C22: 25.426 | D22: 25.426 | E22: 25.426 | F22: 25.426 | G22: 35.426
B23: III. Gewinnrücklagen | C23: 25.131 | D23: 25.131 | E23: 35.131 | F23: 35.131 | G23: 35.131
B24: IV. Bilanzgewinn | C24: 0 | D24: 0 | E24: 0 | F24: 0 | G24: 0
B26: B. Empfangene Ertragszuschüsse | C26: 28.577 | D26: 28.9 | E26: 28.009 | F26: 27.685 | G26: 29.619
B27: C. Rückstellungen (5) | C27: 95.422 | D27: 90.794 | E27: 111.63 | F27: 91.974 | G27: 92.117
B28: D. Verbindlichkeiten (6) | C28: 144.38 | D28: 183.564 | E28: 214.912 | F28: 212.874 | G28: 221.277
B29: davon gegenüber Kreditinstituten | C29: 79 | D29: 98.659 | E29: 110.748 | F29: 119.911 | G29: 124.179
B30: E. Rechnungsabgrenzungsposten | C30: 0.024 | D30: 0 | E30: 0.066 | F30: 0 | G30: 0
B31: Bilanzsumme Passiva | C31: =C20+C26+C27+C28+C30 | D31: =D20+D26+D27+D28+D30 | E31: =E20+E26+E27+E28+E30 | F31: =F20+F26+F27+F28+F30 | G31: =G20+G26+G27+G28+G30
B33: Kontrolle: Bilanzsumme Aktiva ./. Passiva (muss 0 sein) | C33: =ROUND(C17-C31,6) | D33: =ROUND(D17-D31,6) | E33: =ROUND(E17-E31,6) | F33: =ROUND(F17-F31,6) | G33: =ROUND(G17-G31,6)
B35: Quelle: Unternehmensregister – ESWE Versorgungs AG, Wiesbaden, HRB 2105 (Amtsgericht Wiesbaden): Jahresabschluss 2021 (GJ 2021), 2022 (GJ 2022), 2023 (GJ 2023) und 2024 (GJ 2024); Geschäftsbericht 2025, Seite 73 (GJ 2025). Beträge in T€ veröffentlicht und hier in EUR Mio. dargestellt. Die Position „davon gegenüber Kreditinstituten“ stammt aus dem Verbindlichkeitenspiegel im Anhang (JA 2021 S. 17, JA 2022 S. 18, JA 2023 S. 8, JA 2024 S. 7, GB 2025 S. 82) und ist nachrichtlich ausgewiesen; sie geht nicht in die Bilanzsumme ein.

Sheet ESWE GuV
B2: ESWE Versorgungs AG – Gewinn- und Verlustrechnung 2021–2025
B3: EUR Mio. | C3: 2021 | D3: =C3+1 | E3: =D3+1 | F3: =E3+1 | G3: =F3+1
B5: 1. Umsatzerlöse (10) | C5: 426.532 | D5: 475.683 | E5: 634.062 | F5: 534.653 | G5: 473.77
B6: 2. Veränderung des Bestands an unfertigen Leistungen | C6: -0.332 | D6: 0.86 | E6: 0.811 | F6: 0.069 | G6: -0.545
B7: 3. Andere aktivierte Eigenleistungen (11) | C7: 3.399 | D7: 3.309 | E7: 1.873 | F7: 2.674 | G7: 2.992
B8: 4. Sonstige betriebliche Erträge (12) | C8: 2.486 | D8: 5.989 | E8: 6.383 | F8: 30.279 | G8: 9.708
B9: 5. Materialaufwand (13) | C9: 311.386 | D9: 356.302 | E9: 483.927 | F9: 387.16 | G9: 341.791
B10: 6. Personalaufwand (14) | C10: 50.803 | D10: 52.128 | E10: 52.026 | F10: 55.317 | G10: 60.837
B11: 7. Abschreibungen (15) | C11: 14.18 | D11: 14.545 | E11: 14.57 | F11: 15.673 | G11: 16.427
B12: 8. Sonstige betriebliche Aufwendungen (16) | C12: 35.338 | D12: 26.581 | E12: 49.684 | F12: 36.261 | G12: 38.141
B13: 9. Betriebliches Ergebnis | C13: =SUM(C5:C8)-SUM(C9:C12) | D13: =SUM(D5:D8)-SUM(D9:D12) | E13: =SUM(E5:E8)-SUM(E9:E12) | F13: =SUM(F5:F8)-SUM(F9:F12) | G13: =SUM(G5:G8)-SUM(G9:G12)
B15: 10. Beteiligungsergebnis (17) | C15: 24.466 | D15: 17.558 | E15: 30.534 | F15: 17.765 | G15: 25.06
B16: 11. Abschreibungen auf Finanzanlagen (18) | C16: 0 | D16: 2.037 | E16: 0 | F16: 8.965 | G16: 0.388
B17: 12. Zinsergebnis (19) | C17: -0.767 | D17: -0.049 | E17: 1.281 | F17: 2.218 | G17: -0.751
B18: 13. Ergebnis vor Steuern | C18: =C13+C15-C16+C17 | D18: =D13+D15-D16+D17 | E18: =E13+E15-E16+E17 | F18: =F13+F15-F16+F17 | G18: =G13+G15-G16+G17
B20: 14. Steuern vom Einkommen und vom Ertrag (20) | C20: 3.034 | D20: 3.214 | E20: 3.939 | F20: 5.544 | G20: 3.494
B21: 15. Ergebnis nach Steuern | C21: =C18-C20 | D21: =D18-D20 | E21: =E18-E20 | F21: =F18-F20 | G21: =G18-G20
B23: 16. Sonstige Steuern (21) | C23: 0.3 | D23: 0.308 | E23: 0.237 | F23: 0.44 | G23: 0.271
B24: 17. Unternehmensergebnis / Jahresüberschuss | C24: =C21-C23 | D24: =D21-D23 | E24: =E21-E23 | F24: =F21-F23 | G24: =G21-G23
B26: 18. Einstellung in die anderen Gewinnrücklagen (22) | C26: 0 | D26: 0 | E26: 10 | F26: 0 | G26: 0
B27: 19. Aufwendungen für Ausgleichszahlung | C27: 16.295 | D27: 17.312 | E27: 21.109 | F27: 29.779 | G27: 18.768
B28: 20. Aufgrund eines Ergebnisabführungsvertrags abgeführter Gewinn | C28: 24.448 | D28: 30.923 | E28: 39.452 | F28: 48.519 | G28: 30.117
B29: 21. Bilanzgewinn | C29: =C24-SUM(C26:C28) | D29: =D24-SUM(D26:D28) | E29: =E24-SUM(E26:E28) | F29: =F24-SUM(F26:F28) | G29: =G24-SUM(G26:G28)
B31: Kontrolle: Bilanzgewinn GuV ./. Bilanzgewinn Bilanz (muss 0 sein) | C31: =ROUND(C29-'ESWE Bilanz'!C24,6) | D31: =ROUND(D29-'ESWE Bilanz'!D24,6) | E31: =ROUND(E29-'ESWE Bilanz'!E24,6) | F31: =ROUND(F29-'ESWE Bilanz'!F24,6) | G31: =ROUND(G29-'ESWE Bilanz'!G24,6)
B33: Quelle: Unternehmensregister – ESWE Versorgungs AG, HRB 2105, Jahresabschlüsse 2021 bis 2024; Geschäftsbericht 2025, Seite 74 (GJ 2025). Die Positionsnummerierung folgt dem Jahresabschluss 2024. Die Gewinn- und Verlustrechnung 2025 weist die Position „Einstellung in die anderen Gewinnrücklagen“ nicht aus; sie ist für 2025 mit null angesetzt, wodurch die Gliederung über alle fünf Jahre einheitlich bleibt und der Bilanzgewinn in jedem Jahr auf null überleitet.

Sheet ESWE Cashflow
B2: ESWE Versorgungs AG – Kapitalflussrechnung nach DRS 21 2021–2025
B3: EUR Mio. | C3: 2021 | D3: =C3+1 | E3: =D3+1 | F3: =E3+1 | G3: =F3+1
B5: (+) Cashflow aus laufender Geschäftstätigkeit | C5: 49 | D5: 78 | E5: 47.3 | F5: 68.2 | G5: 42.7
B6: (+) Cashflow aus der Investitionstätigkeit | C6: -19.5 | D6: -34 | E6: 8.9 | F6: -5 | G6: -8.3
B7: (+) Cashflow aus der Finanzierungstätigkeit | C7: -28.9 | D7: -17 | E7: -41.8 | F7: -86.7 | G7: -53.4
B9: (=) Zahlungswirksame Veränderung des Finanzmittelfonds | C9: =SUM(C5:C7) | D9: =SUM(D5:D7) | E9: =SUM(E5:E7) | F9: =SUM(F5:F7) | G9: =SUM(G5:G7)
B10: (+) Finanzmittelfonds am Anfang der Periode | C10: 3 | D10: 3.6 | E10: 30.6 | F10: 45 | G10: 21.5
B11: Finanzmittelfonds am Ende der Periode | C11: =C10+C9 | D11: =D10+D9 | E11: =E10+E9 | F11: =F10+F9 | G11: =G10+G9
B13: nachrichtlich: veröffentlichter Endbestand lt. Lagebericht | C13: 3.6 | D13: 30.6 | E13: 45 | F13: 21.5 | G13: 2.5
B14: Kontrolle: berechneter ./. veröffentlichter Endbestand (muss 0 sein) | C14: =ROUND(C11-C13,1) | D14: =ROUND(D11-D13,1) | E14: =ROUND(E11-E13,1) | F14: =ROUND(F11-F13,1) | G14: =ROUND(G11-G13,1)
B15: Kontrolle: Endbestand ./. Kassenbestand lt. Bilanz (muss 0 sein) | C15: =ROUND(C11-'ESWE Bilanz'!C14,1) | D15: =ROUND(D11-'ESWE Bilanz'!D14,1) | E15: =ROUND(E11-'ESWE Bilanz'!E14,1) | F15: =ROUND(F11-'ESWE Bilanz'!F14,1) | G15: =ROUND(G11-'ESWE Bilanz'!G14,1)
B17: Quelle: Lagebericht im jeweiligen Jahresabschluss (JA 2022 für GJ 2021 und 2022, JA 2023 S. 25, JA 2024 S. 26) sowie Geschäftsbericht 2025, Seite 18 (GJ 2024 und 2025). Die Gesellschaft veröffentlicht die Kapitalflussrechnung ausschließlich in dieser verkürzten Form; eine Überleitung der einzelnen DRS-21-Posten (Jahresergebnis, Abschreibungen, Working-Capital-Veränderungen usw.) ist aus den veröffentlichten Abschlüssen nicht ableitbar. Für 2022 nennt der JA 2022 abweichend 95,4 / -44,9 / -23,5 Mio. €; angesetzt sind die Werte des JA 2023 – die Summe ist in beiden Fassungen identisch (Umgliederung).

Sheet ESWE KPIs
B2: ESWE Versorgungs AG – Key Financials 2021–2025
B3: EUR Mio. / % / x | C3: 2021 | D3: =C3+1 | E3: =D3+1 | F3: =E3+1 | G3: =F3+1
B5: Umsatzerlöse | C5: ='ESWE GuV'!C5 | D5: ='ESWE GuV'!D5 | E5: ='ESWE GuV'!E5 | F5: ='ESWE GuV'!F5 | G5: ='ESWE GuV'!G5
B6: Gesamtleistung | C6: ='ESWE GuV'!C5+'ESWE GuV'!C6+'ESWE GuV'!C7 | D6: ='ESWE GuV'!D5+'ESWE GuV'!D6+'ESWE GuV'!D7 | E6: ='ESWE GuV'!E5+'ESWE GuV'!E6+'ESWE GuV'!E7 | F6: ='ESWE GuV'!F5+'ESWE GuV'!F6+'ESWE GuV'!F7 | G6: ='ESWE GuV'!G5+'ESWE GuV'!G6+'ESWE GuV'!G7
B7: Rohertrag | C7: =C6-'ESWE GuV'!C9 | D7: =D6-'ESWE GuV'!D9 | E7: =E6-'ESWE GuV'!E9 | F7: =F6-'ESWE GuV'!F9 | G7: =G6-'ESWE GuV'!G9
B8: (%) Rohertragsmarge | C8: =IFERROR(C7/C6,0) | D8: =IFERROR(D7/D6,0) | E8: =IFERROR(E7/E6,0) | F8: =IFERROR(F7/F6,0) | G8: =IFERROR(G7/G6,0)
B10: EBITDA | C10: =C11+'ESWE GuV'!C11 | D10: =D11+'ESWE GuV'!D11 | E10: =E11+'ESWE GuV'!E11 | F10: =F11+'ESWE GuV'!F11 | G10: =G11+'ESWE GuV'!G11
B11: EBIT / Betriebliches Ergebnis | C11: ='ESWE GuV'!C13 | D11: ='ESWE GuV'!D13 | E11: ='ESWE GuV'!E13 | F11: ='ESWE GuV'!F13 | G11: ='ESWE GuV'!G13
B12: Beteiligungsergebnis | C12: ='ESWE GuV'!C15 | D12: ='ESWE GuV'!D15 | E12: ='ESWE GuV'!E15 | F12: ='ESWE GuV'!F15 | G12: ='ESWE GuV'!G15
B13: Zinsergebnis | C13: ='ESWE GuV'!C17 | D13: ='ESWE GuV'!D17 | E13: ='ESWE GuV'!E17 | F13: ='ESWE GuV'!F17 | G13: ='ESWE GuV'!G17
B14: Ergebnis vor Steuern | C14: ='ESWE GuV'!C18 | D14: ='ESWE GuV'!D18 | E14: ='ESWE GuV'!E18 | F14: ='ESWE GuV'!F18 | G14: ='ESWE GuV'!G18
B15: Jahresüberschuss | C15: ='ESWE GuV'!C24 | D15: ='ESWE GuV'!D24 | E15: ='ESWE GuV'!E24 | F15: ='ESWE GuV'!F24 | G15: ='ESWE GuV'!G24
B17: OCF – Operating Cash Flow | C17: ='ESWE Cashflow'!C5 | D17: ='ESWE Cashflow'!D5 | E17: ='ESWE Cashflow'!E5 | F17: ='ESWE Cashflow'!F5 | G17: ='ESWE Cashflow'!G5
B18: ICF – Investing Cash Flow | C18: ='ESWE Cashflow'!C6 | D18: ='ESWE Cashflow'!D6 | E18: ='ESWE Cashflow'!E6 | F18: ='ESWE Cashflow'!F6 | G18: ='ESWE Cashflow'!G6
B19: FCF – Financing Cash Flow | C19: ='ESWE Cashflow'!C7 | D19: ='ESWE Cashflow'!D7 | E19: ='ESWE Cashflow'!E7 | F19: ='ESWE Cashflow'!F7 | G19: ='ESWE Cashflow'!G7
B20: FFCF – Free Cash Flow (OCF + ICF) | C20: =C17+C18 | D20: =D17+D18 | E20: =E17+E18 | F20: =F17+F18 | G20: =G17+G18
B22: Bilanzsumme | C22: ='ESWE Bilanz'!C17 | D22: ='ESWE Bilanz'!D17 | E22: ='ESWE Bilanz'!E17 | F22: ='ESWE Bilanz'!F17 | G22: ='ESWE Bilanz'!G17
B23: Eigenkapital | C23: ='ESWE Bilanz'!C20 | D23: ='ESWE Bilanz'!D20 | E23: ='ESWE Bilanz'!E20 | F23: ='ESWE Bilanz'!F20 | G23: ='ESWE Bilanz'!G20
B24: (%) Eigenkapitalquote | C24: =IFERROR(C23/C22,0) | D24: =IFERROR(D23/D22,0) | E24: =IFERROR(E23/E22,0) | F24: =IFERROR(F23/F22,0) | G24: =IFERROR(G23/G22,0)
B25: (%) Anlagenintensität | C25: =IFERROR('ESWE Bilanz'!C6/C22,0) | D25: =IFERROR('ESWE Bilanz'!D6/D22,0) | E25: =IFERROR('ESWE Bilanz'!E6/E22,0) | F25: =IFERROR('ESWE Bilanz'!F6/F22,0) | G25: =IFERROR('ESWE Bilanz'!G6/G22,0)
B26: (%) Umsatzrendite | C26: =IFERROR(C15/C5,0) | D26: =IFERROR(D15/D5,0) | E26: =IFERROR(E15/E5,0) | F26: =IFERROR(F15/F5,0) | G26: =IFERROR(G15/G5,0)
B27: (-) Kassenbestand | C27: ='ESWE Bilanz'!C14 | D27: ='ESWE Bilanz'!D14 | E27: ='ESWE Bilanz'!E14 | F27: ='ESWE Bilanz'!F14 | G27: ='ESWE Bilanz'!G14
B28: (+) Verbindlichkeiten gegenüber Kreditinstituten | C28: ='ESWE Bilanz'!C29 | D28: ='ESWE Bilanz'!D29 | E28: ='ESWE Bilanz'!E29 | F28: ='ESWE Bilanz'!F29 | G28: ='ESWE Bilanz'!G29
B29: Net Debt | C29: =C28-C27 | D29: =D28-D27 | E29: =E28-E27 | F29: =F28-F27 | G29: =G28-G27
B30: Net Debt / EBITDA | C30: =IFERROR(C29/C10,0) | D30: =IFERROR(D29/D10,0) | E30: =IFERROR(E29/E10,0) | F30: =IFERROR(F29/F10,0) | G30: =IFERROR(G29/G10,0)
B32: Capex (Gesamtinvestitionen inkl. Finanzanlagen) | C32: ='ESWE Capex Revenue'!C14 | D32: ='ESWE Capex Revenue'!D14 | E32: ='ESWE Capex Revenue'!E14 | F32: ='ESWE Capex Revenue'!F14 | G32: ='ESWE Capex Revenue'!G14
B33: (%) Capex / Umsatzerlöse | C33: =IFERROR(C32/C5,0) | D33: =IFERROR(D32/D5,0) | E33: =IFERROR(E32/E5,0) | F33: =IFERROR(F32/F5,0) | G33: =IFERROR(G32/G5,0)
B35: Absatzmengen | C35: 2021 | D35: 2022 | E35: 2023 | F35: 2024 | G35: 2025
B36: Strom (Mio. kWh) | C36: ='ESWE Capex Revenue'!C18 | D36: ='ESWE Capex Revenue'!D18 | E36: ='ESWE Capex Revenue'!E18 | F36: ='ESWE Capex Revenue'!F18 | G36: ='ESWE Capex Revenue'!G18
B37: Gas (Mio. kWh) | C37: ='ESWE Capex Revenue'!C19 | D37: ='ESWE Capex Revenue'!D19 | E37: ='ESWE Capex Revenue'!E19 | F37: ='ESWE Capex Revenue'!F19 | G37: ='ESWE Capex Revenue'!G19
B38: Wärme / Kälte (Mio. kWh) | C38: ='ESWE Capex Revenue'!C20 | D38: ='ESWE Capex Revenue'!D20 | E38: ='ESWE Capex Revenue'!E20 | F38: ='ESWE Capex Revenue'!F20 | G38: ='ESWE Capex Revenue'!G20
B39: Wassernetz (Mio. m³) | C39: ='ESWE Capex Revenue'!C21 | D39: ='ESWE Capex Revenue'!D21 | E39: ='ESWE Capex Revenue'!E21 | F39: ='ESWE Capex Revenue'!F21 | G39: ='ESWE Capex Revenue'!G21
B41: Net Debt = Verbindlichkeiten gegenüber Kreditinstituten abzüglich Kassenbestand und Guthaben bei Kreditinstituten (Methodik des evm/enm Financial Model). EBITDA = Betriebliches Ergebnis zzgl. Abschreibungen auf immaterielle Vermögensgegenstände und Sachanlagen; Abschreibungen auf Finanzanlagen sind nicht enthalten, da sie unterhalb des Betriebsergebnisses ausgewiesen werden. Anlagenintensität = Anlagevermögen / Bilanzsumme. Umsatzrendite = Jahresüberschuss / Umsatzerlöse.

Sheet ESWE Capex Revenue
B2: ESWE Versorgungs AG – Investitionen, Umsatzerlöse und Absatz 2021–2025
B3: EUR Mio. / Mio. kWh / Mio. m³ | C3: 2021 | D3: =C3+1 | E3: =D3+1 | F3: =E3+1 | G3: =F3+1
B5: Investitionen nach Unternehmensbereichen
B6: Stromversorgung | C6: 2.876 | D6: 2.173 | E6: 1.005 | F6: 0.568 | G6: 0.982
B7: Gasversorgung | C7: 9.439 | D7: 4.249 | E7: 2.139 | F7: 2.393 | G7: 2.991
B8: Wasserversorgung | C8: 7.505 | D8: 11.746 | E8: 5.922 | F8: 7.867 | G8: 13.969
B9: Wärmeversorgung | C9: 7.456 | D9: 8.593 | E9: 9.995 | F9: 8.561 | G9: 6.503
B10: Telekommunikation | C10: n.a. | D10: n.a. | E10: n.a. | F10: 1.259 | G10: n.a.
B11: Sonstige Bereiche | C11: 1.748 | D11: 1.059 | E11: 0.814 | F11: 1.173 | G11: 3.377
B12: Gemeinsame Bereiche | C12: n.a. | D12: 1.851 | E12: 5.599 | F12: 3.426 | G12: 3.957
B13: Beteiligungen (Finanzanlagen) | C13: 14.169 | D13: 24.003 | E13: 1.868 | F13: 2.206 | G13: 5.229
B14: Gesamtinvestitionen | C14: =SUM(C6:C13) | D14: =SUM(D6:D13) | E14: =SUM(E6:E13) | F14: =SUM(F6:F13) | G14: =SUM(G6:G13)
B16: Absatzmengen
B18: Strom (Mio. kWh) | C18: 946 | D18: 877 | E18: 731 | F18: 609 | G18: 605
B19: Gas (Mio. kWh) | C19: 2220 | D19: 1811 | E19: 1545 | F19: 1461 | G19: 1445
B20: Wärme / Kälte (Mio. kWh) | C20: 295 | D20: 256 | E20: 238 | F20: 272 | G20: 275
B21: Wassernetz (Mio. m³) | C21: 14.4 | D21: 14.5 | E21: 14.3 | F21: 14.6 | G21: 14.7
B23: Umsatzerlöse nach Unternehmensbereichen
B24: Stromversorgung (inkl. Handelsgeschäfte) | C24: 215.722 | D24: 207.826 | E24: 268.87 | F24: 200.133 | G24: 190
B25: Gasversorgung (inkl. Handelsgeschäfte) | C25: 108.195 | D25: 156.251 | E25: 241.101 | F25: 206.042 | G25: 155.7
B26: Wärmeversorgung | C26: 30.495 | D26: 35.26 | E26: 40.545 | F26: 45.961 | G26: 43.7
B27: Betriebsführung Wasserversorgung | C27: 23.863 | D27: 24.698 | E27: 25.771 | F27: 29.842 | G27: 32.6
B28: Wasserverkauf an WLW | C28: 12.672 | D28: 15.355 | E28: 17.394 | F28: 15.831 | G28: 16.9
B29: Konzerninterne Dienstleistungen | C29: 22.855 | D29: 21.16 | E29: 22.017 | F29: 21.457 | G29: 20.2
B30: Übrige Umsatzerlöse | C30: 12.73 | D30: 15.133 | E30: 18.364 | F30: 15.387 | G30: 14.7
B31: Umsätze lt. Aufteilung | C31: =SUM(C24:C30) | D31: =SUM(D24:D30) | E31: =SUM(E24:E30) | F31: =SUM(F24:F30) | G31: =SUM(G24:G30)
B32: nachrichtlich: Umsatzerlöse lt. GuV | C32: ='ESWE GuV'!C5 | D32: ='ESWE GuV'!D5 | E32: ='ESWE GuV'!E5 | F32: ='ESWE GuV'!F5 | G32: ='ESWE GuV'!G5
B33: Kontrolle: Aufteilung ./. GuV (muss 0 sein; 2025 Rundung) | C33: =ROUND(C31-C32,1) | D33: =ROUND(D31-D32,1) | E33: =ROUND(E31-E32,1) | F33: =ROUND(F31-F32,1) | G33: =ROUND(G31-G32,1)
B35: Umsatzaufteilung in Prozent
B36: Stromversorgung (inkl. Handelsgeschäfte) | C36: =IFERROR(C24/C$31,0) | D36: =IFERROR(D24/D$31,0) | E36: =IFERROR(E24/E$31,0) | F36: =IFERROR(F24/F$31,0) | G36: =IFERROR(G24/G$31,0)
B37: Gasversorgung (inkl. Handelsgeschäfte) | C37: =IFERROR(C25/C$31,0) | D37: =IFERROR(D25/D$31,0) | E37: =IFERROR(E25/E$31,0) | F37: =IFERROR(F25/F$31,0) | G37: =IFERROR(G25/G$31,0)
B38: Wärmeversorgung | C38: =IFERROR(C26/C$31,0) | D38: =IFERROR(D26/D$31,0) | E38: =IFERROR(E26/E$31,0) | F38: =IFERROR(F26/F$31,0) | G38: =IFERROR(G26/G$31,0)
B39: Betriebsführung Wasserversorgung | C39: =IFERROR(C27/C$31,0) | D39: =IFERROR(D27/D$31,0) | E39: =IFERROR(E27/E$31,0) | F39: =IFERROR(F27/F$31,0) | G39: =IFERROR(G27/G$31,0)
B40: Wasserverkauf an WLW | C40: =IFERROR(C28/C$31,0) | D40: =IFERROR(D28/D$31,0) | E40: =IFERROR(E28/E$31,0) | F40: =IFERROR(F28/F$31,0) | G40: =IFERROR(G28/G$31,0)
B41: Konzerninterne Dienstleistungen | C41: =IFERROR(C29/C$31,0) | D41: =IFERROR(D29/D$31,0) | E41: =IFERROR(E29/E$31,0) | F41: =IFERROR(F29/F$31,0) | G41: =IFERROR(G29/G$31,0)
B42: Übrige Umsatzerlöse | C42: =IFERROR(C30/C$31,0) | D42: =IFERROR(D30/D$31,0) | E42: =IFERROR(E30/E$31,0) | F42: =IFERROR(F30/F$31,0) | G42: =IFERROR(G30/G$31,0)
B43: Summe | C43: =SUM(C36:C42) | D43: =SUM(D36:D42) | E43: =SUM(E36:E42) | F43: =SUM(F36:F42) | G43: =SUM(G36:G42)
B45: Quelle Investitionen: Lagebericht des jeweiligen Jahresabschlusses (JA 2021 S. 5, JA 2022 S. 6, JA 2023 S. 24, JA 2024 S. 25) sowie Geschäftsbericht 2025, Seite 18. Angesetzt ist jeweils die Darstellung des Berichtsjahres selbst. „n.a.“ bedeutet, dass der Bereich im betreffenden Jahr nicht separat ausgewiesen wurde – dies ist nicht mit einem Wert von null gleichzusetzen: 2021 waren die gemeinsamen Bereiche noch auf die Sparten verteilt, die Telekommunikation wurde nur im Jahresabschluss 2024 gesondert gezeigt.
B48: Quelle Umsatzaufteilung: „Aufteilung nach Bereichen“ im Lagebericht (JA 2021 S. 19, JA 2022 S. 20, JA 2023 S. 10, JA 2024 S. 9) sowie Geschäftsbericht 2025, Seite 16. Die Aufteilung 2025 wird nur auf 0,1 Mio. € genau veröffentlicht; die Summe der Sparten (473,8) weicht daher um 0,03 Mio. € vom GuV-Umsatz (473,770) ab. Quelle Absatzmengen: „Absatzentwicklung“ im jeweiligen Lagebericht bzw. Geschäftsbericht 2025, Seite 15.

Sheet Quellen & Hinweise
B2: ESWE Versorgungs AG – Quellen und Hinweise
B3: Gegenstand | C3: Erläuterung
B4: Gesellschaft | C4: ESWE Versorgungs AG, Konradinerallee 25, 65189 Wiesbaden – Amtsgericht Wiesbaden, HRB 2105.
B5: Berichtsumfang | C5: Dargestellt ist ausschließlich der HGB-Einzelabschluss der Geschäftsjahre 2021 bis 2025. Die Tätigkeitsabschlüsse nach § 6b EnWG sind nicht Bestandteil dieser Auswertung.
C6: Ein Konzernabschluss wird nicht aufgestellt (§ 291 Abs. 1 HGB – Einbeziehung in den Konzernabschluss der WVV Wiesbaden Holding GmbH).
B7: Quelle GJ 2021 | C7: Jahres- und Tätigkeitsabschluss nach EnWG zum 31.12.2021, Auszug aus dem Unternehmensregister.
B8: Quelle GJ 2022 | C8: Jahres- und Tätigkeitsabschluss nach EnWG zum 31.12.2022, Auszug aus dem Unternehmensregister.
B9: Quelle GJ 2023 | C9: Jahresabschluss zum 31.12.2023 und Tätigkeitsabschluss, Auszug aus dem Unternehmensregister.
B10: Quelle GJ 2024 | C10: Jahres- und Tätigkeitsabschluss nach EnWG zum 31.12.2024, Tag der Erstellung 16.01.2026.
B11: Quelle GJ 2025 | C11: Bericht über das Geschäftsjahr 2025 (Geschäftsbericht), ESWE Versorgungs AG – Bilanz S. 73, Gewinn- und Verlustrechnung S. 74, Kapitalflussrechnung und Investitionen S. 18, Umsatzaufteilung S. 16, Absatz S. 15, Verbindlichkeitenspiegel S. 82.
B12: Darstellungseinheit | C12: Die Abschlüsse werden in T€ veröffentlicht. In dieser Mappe sind sämtliche Beträge in EUR Mio. dargestellt, um dem Financial Model der evm AG / enm zu entsprechen. Die Werte sind exakt hinterlegt (T€ / 1.000) und lediglich auf eine Nachkommastelle gerundet angezeigt; alle Summen und Kontrollen rechnen mit den vollen Werten.
B13: Farbkonvention | C13: Blau = Eingabewert direkt aus dem Abschluss | Schwarz = Formel im Blatt | Grün = Verweis auf ein anderes Blatt | Grau kursiv = im betreffenden Jahr nicht separat ausgewiesen (n.a.).
B14: Abweichung 1 | C14: Kapitalflussrechnung 2022: Der JA 2022 nennt 95,4 / -44,9 / -23,5 Mio. €, der JA 2023 für dasselbe Jahr 78,0 / -34,0 / -17,0 Mio. €. Die Summe (27,0 Mio. €) ist in beiden Fassungen identisch – es handelt sich um eine Umgliederung zwischen den Cashflow-Bereichen. Angesetzt sind die Werte des JA 2023.
B15: Abweichung 2 | C15: Verbindlichkeiten gegenüber Kreditinstituten 2025: Der Lagebericht (GB 2025 S. 20) nennt 123,7 Mio. €, der Verbindlichkeitenspiegel im Anhang (S. 82) 124.179 T€. Angesetzt ist der Anhangwert, da er mit der Summe der Verbindlichkeiten von 221.277 T€ in der Bilanz zusammenpasst.
B16: Abweichung 3 | C16: Investitionen nach Unternehmensbereichen: Der JA 2024 weist eine eigene Zeile „Telekommunikation“ (2024: 1.259 T€; 2023: 919 T€) aus und nennt für 2023 abweichend vom JA 2023 Strom 524 statt 1.005 T€ und Sonstige 376 statt 814 T€. Der GB 2025 verzichtet auf die Zeile Telekommunikation und zeigt in der Vergleichsspalte 2024 Strom 1.259 und Sonstige 1.741 T€. Die Gesamtsummen (27.342 bzw. 27.453 T€) stimmen in allen Fassungen überein. Angesetzt ist jeweils die Darstellung des Berichtsjahres selbst.
B17: Abweichung 4 | C17: Ergebnis vor Steuern: Der Lagebericht des GB 2025 nennt für 2025 52,4 Mio. € und für 2024 83,8 Mio. €. Diese Werte stammen aus der betriebswirtschaftlichen Kurzfassung der Ertragslage und weichen von der handelsrechtlichen GuV ab (52.650 bzw. 84.282 T€). Angesetzt sind durchgehend die Werte der GuV.
B18: GuV-Gliederung | C18: Die Positionsnummerierung folgt dem Jahresabschluss 2024. Die GuV 2025 kennt die Position „Einstellung in die anderen Gewinnrücklagen“ nicht; sie ist für 2025 mit null angesetzt, damit die Gliederung über alle fünf Jahre einheitlich ist.
... B20: Formatvorlage | C20: Aufbau, Schriftart (Univers for Metzler), Schriftgrößen, Rahmen, Farben und Zahlenformate sind aus evm_enm_financial_model_2020_2024_v5 übernommen: Titelbanner weiß auf 003D7C, Kopfzeile weiß auf 3157E3, Zahlenformat #,##0.0 mit Klammern für negative Werte und „–“ für null, Prozente 0,0 %, Vielfache 0,0x, Spalte A als Randspalte, Kennzahlenblöcke durch dünne Linien getrennt.
